{"title":"未命名演示文稿","width":1000,"height":562.5,"theme":{"themeColors":["rgb(155, 0, 0)"],"fontColor":"rgb(51, 51, 51)","fontName":"","backgroundColor":"rgb(255, 255, 255)","shadow":{"h":3,"v":3,"blur":2,"color":"#808080"},"outline":{"width":2,"color":"#525252","style":"solid"}},"slides":[{"id":"kXIk-2p5GV","elements":[{"type":"shape","id":"08eMhOIES5","left":0,"top":0,"width":1000,"height":281.25,"viewBox":[200,200],"path":"M 0 0 L 200 0 L 200 200 L 0 200 Z","fill":"rgb(155, 0, 0)","fixedRatio":false,"rotate":0,"lock":true},{"type":"shape","id":"CZdIjR_Gpv","left":0,"top":281.25,"width":1000,"height":281.25,"viewBox":[200,200],"path":"M 0 0 L 200 0 L 200 200 L 0 200 Z","fill":"rgb(242, 242, 242)","fixedRatio":false,"rotate":0,"lock":true},{"type":"shape","id":"EQDezgGTee","left":40,"top":40,"width":920,"height":482,"viewBox":[200,200],"path":"M 0 0 L 200 0 L 200 200 L 0 200 Z","fill":"#ffffff","fixedRatio":false,"rotate":0,"shadow":{"h":4,"v":4,"blur":8,"color":"rgba(128, 128, 128, 0.13)"},"lock":true},{"type":"text","id":"vw6nysUqHb","left":90.00000000000006,"top":170,"width":820,"height":101,"content":"<p style=\"text-align: center;\"><strong><span style=\"font-size: 54px;\">模板封面标题</span></strong></p>","rotate":0,"defaultFontName":"","defaultColor":"#333","vertical":false,"textType":"title"},{"type":"text","id":"sO32lih4vG","left":90,"top":292.1268090154214,"width":820,"height":68,"content":"<p style=\"text-align: center;\"><span style=\"font-size: 16px;\">模板封面正文模板封面正文模板封面正文模板封面正文模板封面正文模板封面正文模板封面正文模板封面正文模板封面正文模板封面正文模板封面正文模板封面正文模板封面正文</span></p>","rotate":0,"defaultFontName":"","defaultColor":"#333","vertical":false,"textType":"content"},{"type":"line","id":"7F6wpKv3mT","left":395.08600237247924,"top":281.41660735468577,"start":[0,0],"end":[209.82799525504151,0],"points":["",""],"color":"rgb(155, 0, 0)","style":"solid","width":1},{"type":"text","id":"e1tf1Fv94x","left":420,"top":410,"width":160,"height":44,"content":"<p style=\"text-align: center;\"><em><span style=\"font-size: 16px;\">演讲人：XXX</span></em></p>","rotate":0,"defaultFontName":"","defaultColor":"#333","vertical":false},{"type":"shape","id":"KprH-Gfy2J","left":53.347697953736684,"top":472.90878929418744,"width":36.65230204626337,"height":36.65230204626337,"viewBox":[36.65230204626337,36.65230204626337],"path":"M 0 0 L 0 36.65230204626337 L 36.65230204626337 36.65230204626337 L 36.65230204626337 32.98707184163703 L 3.6652302046263374 32.98707184163703 L 3.6652302046263374 0 Z","fill":"rgb(155, 0, 0)","fixedRatio":false,"rotate":0,"pathFormula":"L","keypoints":[0.1],"lock":true},{"type":"shape","id":"bOi5kaJXbz","left":910,"top":472.90878929418744,"width":36.65230204626337,"height":36.65230204626337,"viewBox":[36.65230204626337,36.65230204626337],"path":"M 0 0 L 0 36.65230204626337 L 36.65230204626337 36.65230204626337 L 36.65230204626337 32.98707184163703 L 3.6652302046263374 32.98707184163703 L 3.6652302046263374 0 Z","fill":"rgb(155, 0, 0)","fixedRatio":false,"rotate":-90,"pathFormula":"L","keypoints":[0.1],"lock":true},{"type":"shape","id":"HgW-Hf_ji8","left":910,"top":54.37972642348757,"width":36.65230204626337,"height":36.65230204626337,"viewBox":[36.65230204626337,36.65230204626337],"path":"M 0 0 L 0 36.65230204626337 L 36.65230204626337 36.65230204626337 L 36.65230204626337 32.98707184163703 L 3.6652302046263374 32.98707184163703 L 3.6652302046263374 0 Z","fill":"rgb(155, 0, 0)","fixedRatio":false,"rotate":180,"pathFormula":"L","keypoints":[0.1],"lock":true},{"type":"shape","id":"kSRPab7QQJ","left":53.347697953736684,"top":54.37972642348757,"width":36.65230204626337,"height":36.65230204626337,"viewBox":[36.65230204626337,36.65230204626337],"path":"M 0 0 L 0 36.65230204626337 L 36.65230204626337 36.65230204626337 L 36.65230204626337 32.98707184163703 L 3.6652302046263374 32.98707184163703 L 3.6652302046263374 0 Z","fill":"rgb(155, 0, 0)","fixedRatio":false,"rotate":90,"pathFormula":"L","keypoints":[0.1],"lock":true}],"background":{"type":"solid","color":"#fff"},"type":"cover"},{"id":"uJPiN54fD5","elements":[{"type":"image","id":"ZtKNETIb41","src":"https://images.pexels.com/photos/29968980/pexels-photo-29968980.jpeg?auto=compress&cs=tinysrgb&w=600","width":375,"height":562.5,"left":625,"top":0,"fixedRatio":true,"rotate":0,"filters":{"grayscale":"100%","opacity":"100%"},"lock":true,"imageType":"pageFigure"},{"type":"text","id":"Tm1uVcBxFQ","left":35,"top":38,"width":200,"height":80,"content":"<p style=\"\"><span style=\"font-size: 60px;\">目录</span></p>","rotate":0,"defaultFontName":"","defaultColor":"#333","vertical":false,"lineHeight":1},{"type":"text","id":"zqe8Pc3ZuR","left":41.81958036773428,"top":108.77593045670226,"width":240.21352313167262,"height":44,"content":"<p style=\"\"><strong><span style=\"font-size: 24px;\">CONTENTS</span></strong></p>","rotate":0,"defaultFontName":"","defaultColor":"#333","vertical":false,"wordSpace":10,"lineHeight":1},{"type":"shape","id":"NsxV-dUQmA","left":53.16477609727165,"top":160.12468490510082,"width":108.76156583629896,"height":22.24199288256228,"viewBox":[200,200],"path":"M 0 0 L 200 0 L 200 200 L 0 200 Z","fill":"rgb(155, 0, 0)","fixedRatio":false,"rotate":0,"lock":true},{"type":"line","id":"J7kOh8JeiY","left":53.16477609727165,"top":182.3666777876631,"start":[0,0],"end":[509.3416370106761,0],"points":["",""],"color":"rgb(155, 0, 0)","style":"solid","width":2,"lock":true},{"type":"shape","id":"4hYHUNjxcI","left":54.28310349940691,"top":263.3699881376038,"width":50,"height":50,"viewBox":[200,200],"path":"M 0 0 L 200 0 L 200 200 L 0 200 Z","fill":"rgb(155, 0, 0)","fixedRatio":true,"rotate":0,"text":{"content":"<p style=\"text-align: center;\"><strong><span style=\"font-size: 24px;\"><span style=\"color: rgb(255, 255, 255);\">01</span></span></strong></p>","defaultFontName":"","defaultColor":"#000","align":"middle","type":"itemNumber"},"groupId":"PO69sOwIRm"},{"type":"text","id":"JbHXv-jwAp","left":109.78310349940685,"top":260.3699881376038,"width":477.1055753262159,"height":56,"content":"<p style=\"\"><span style=\"font-size: 24px;\">目录项一</span></p>","rotate":0,"defaultFontName":"","defaultColor":"#333","vertical":false,"groupId":"PO69sOwIRm","textType":"item"},{"type":"shape","id":"P-hT-taXfc","left":54.28310349940697,"top":345.0386318703042,"width":50,"height":50,"viewBox":[200,200],"path":"M 0 0 L 200 0 L 200 200 L 0 200 Z","fill":"rgb(155, 0, 0)","fixedRatio":true,"rotate":0,"text":{"content":"<p style=\"text-align: center;\"><strong><span style=\"font-size: 24px;\"><span style=\"color: rgb(255, 255, 255);\">02</span></span></strong></p>","defaultFontName":"","defaultColor":"#000","align":"middle","type":"itemNumber"},"groupId":"A4PgK8VbWv"},{"type":"text","id":"_Mhm8IPoeC","left":109.78310349940685,"top":342.0386318703042,"width":477.1055753262159,"height":56,"content":"<p style=\"\"><span style=\"font-size: 24px;\">目录项二</span></p>","rotate":0,"defaultFontName":"","defaultColor":"#333","vertical":false,"groupId":"A4PgK8VbWv","textType":"item"},{"type":"shape","id":"RRFXpX7dMJ","left":54.283103499406934,"top":426.7072756030046,"width":50,"height":50,"viewBox":[200,200],"path":"M 0 0 L 200 0 L 200 200 L 0 200 Z","fill":"rgb(155, 0, 0)","fixedRatio":true,"rotate":0,"text":{"content":"<p style=\"text-align: center;\"><strong><span style=\"font-size: 24px;\"><span style=\"color: rgb(255, 255, 255);\">03</span></span></strong></p>","defaultFontName":"","defaultColor":"#000","align":"middle","type":"itemNumber"},"groupId":"c_d19VuyFk"},{"type":"text","id":"iebpmfQkLn","left":109.78310349940682,"top":423.7072756030046,"width":477.1055753262159,"height":56,"content":"<p style=\"\"><span style=\"font-size: 24px;\">目录项三</span></p>","rotate":0,"defaultFontName":"","defaultColor":"#333","vertical":false,"groupId":"c_d19VuyFk","textType":"item"}],"background":{"type":"solid","color":"#fff"},"type":"contents"},{"id":"E426hV8TPB","elements":[{"type":"shape","id":"sHB5Z0TbRm","left":0,"top":131.3,"width":20,"height":300,"viewBox":[200,200],"path":"M 0 0 L 200 0 L 200 200 L 0 200 Z","fill":"rgb(155, 0, 0)","fixedRatio":false,"rotate":0,"lock":true},{"type":"shape","id":"obCpHrJ5eb","left":980,"top":131.3,"width":20,"height":300,"viewBox":[200,200],"path":"M 0 0 L 200 0 L 200 200 L 0 200 Z","fill":"rgb(155, 0, 0)","fixedRatio":false,"rotate":0,"lock":true},{"type":"shape","id":"ZKNTwm7eam","left":419.9999999999999,"top":99.53818579478059,"width":160,"height":160,"viewBox":[200,200],"path":"M 100 0 A 50 50 0 1 1 100 200 A 50 50 0 1 1 100 0 Z","fill":"rgb(155, 0, 0)","fixedRatio":true,"rotate":0,"text":{"content":"<p style=\"text-align: center;\"><strong><span style=\"font-size: 72px;\"><span style=\"color: #ffffff;\">01</span></span></strong></p>","defaultFontName":"","defaultColor":"#000","align":"middle","type":"partNumber"}},{"type":"text","id":"7XnqEe6EBD","left":162.2924080664294,"top":266.93118698102023,"width":675.4151838671412,"height":86,"content":"<p style=\"text-align: center;\"><span style=\"font-size: 44px;\">模板小节过渡标题</span></p>","rotate":0,"defaultFontName":"","defaultColor":"#333","vertical":false,"wordSpace":0,"textType":"title"},{"type":"text","id":"nY_Y5AgPud","left":198.99169632265705,"top":363.29999999999995,"width":602.0166073546857,"height":68,"content":"<p style=\"text-align: center;\" class=\"\">模板小节过渡正文模板小节过渡正文模板小节过渡正文模板小节过渡正文模板小节过渡正文模板小节过渡正文模板小节过渡正文</p>","rotate":0,"defaultFontName":"","defaultColor":"#333","vertical":false,"textType":"content"},{"type":"shape","id":"MRlwBbG9G5","left":487.4999999999999,"top":500.35456702253856,"width":25,"height":25,"viewBox":[200,200],"path":"M 0 0 L 80 0 L 200 100 L 80 200 L 0 200 L 120 100 L 0 0 Z","fill":"rgb(155, 0, 0)","fixedRatio":true,"rotate":90,"opacity":1,"lock":true}],"background":{"type":"solid","color":"#fff"},"type":"transition"},{"id":"Xkwy3XOQgX","elements":[{"type":"text","id":"XPJL1bbw-o","left":124.51281138790031,"top":32.950307680901545,"width":832.3871886120996,"height":56,"content":"<p style=\"text-align: right;\"><span style=\"font-size: 36px;\">模板内容页标题</span></p>","rotate":0,"defaultFontName":"","defaultColor":"#333","vertical":false,"lineHeight":1,"textType":"title"},{"type":"shape","id":"4PWDKrLKu_","left":42.1,"top":29.950307680901542,"width":70,"height":70,"viewBox":[200,200],"path":"M 0 0 L 200 0 L 200 200 L 0 200 Z","fill":"rgb(155, 0, 0)","fixedRatio":false,"rotate":0,"lock":true},{"type":"line","id":"4T8faz_fXX","left":42.08950548635823,"top":100.1,"start":[0,0],"end":[904.5077105575326,0],"points":["",""],"color":"rgb(155, 0, 0)","style":"solid","width":2,"lock":true},{"type":"shape","id":"QlIWmgWNpG","left":53.75,"top":42.25030768090154,"width":46.7,"height":46.7,"viewBox":[200,200],"path":"M 0 0 L 80 0 L 200 100 L 80 200 L 0 200 L 120 100 L 0 0 Z","fill":"#ffffff","fixedRatio":false,"rotate":0,"lock":true},{"type":"shape","id":"nkbfFwBXpI","left":272.7745551601424,"top":191.45421115065247,"width":60,"height":60,"viewBox":[200,200],"path":"M 0 0 L 200 0 L 200 200 L 0 200 Z","fill":"rgb(155, 0, 0)","fixedRatio":true,"rotate":0,"text":{"content":"<p style=\"text-align: center;\"><strong><span style=\"font-size: 24px;\"><span style=\"color: rgb(255, 255, 255);\">01</span></span></strong></p>","defaultFontName":"","defaultColor":"#000","align":"middle","type":"itemNumber"},"groupId":"fqWXGZizO0"},{"type":"text","id":"pIge5bxcwH","left":122.77455516014243,"top":256.66298932384336,"width":360,"height":56,"content":"<p style=\"text-align: center;\"><strong><span style=\"font-size: 24px;\">内容项标题</span></strong></p>","rotate":0,"defaultFontName":"","defaultColor":"#333","vertical":false,"groupId":"fqWXGZizO0","textType":"itemTitle"},{"type":"text","id":"KNsQOLhRaW","left":122.77455516014243,"top":312.6629893238434,"width":360,"height":116,"content":"<p style=\"text-align: center;\">内容项正文内容项正文内容项正文内容项正文内容项正文内容项正文内容项正文内容项正文内容项正文内容项正文内容项正文内容项正文内容项正文内容项正文</p>","rotate":0,"defaultFontName":"","defaultColor":"#333","vertical":false,"groupId":"fqWXGZizO0","textType":"item"},{"type":"shape","id":"dYEid3YyXz","left":667.2254448398576,"top":191.45421115065247,"width":60,"height":60,"viewBox":[200,200],"path":"M 0 0 L 200 0 L 200 200 L 0 200 Z","fill":"rgb(155, 0, 0)","fixedRatio":true,"rotate":0,"text":{"content":"<p style=\"text-align: center;\"><strong><span style=\"font-size: 24px;\"><span style=\"color: rgb(255, 255, 255);\">02</span></span></strong></p>","defaultFontName":"","defaultColor":"#000","align":"middle","type":"itemNumber"},"groupId":"J0BVEQOTet"},{"type":"text","id":"4qw7f6CoRU","left":517.2254448398576,"top":256.66298932384336,"width":360,"height":56,"content":"<p style=\"text-align: center;\"><strong><span style=\"font-size: 24px;\">内容项标题</span></strong></p>","rotate":0,"defaultFontName":"","defaultColor":"#333","vertical":false,"groupId":"J0BVEQOTet","textType":"itemTitle"},{"type":"text","id":"Mf4Hq7P1_-","left":517.2254448398576,"top":312.6629893238434,"width":360,"height":116,"content":"<p style=\"text-align: center;\">内容项正文内容项正文内容项正文内容项正文内容项正文内容项正文内容项正文内容项正文内容项正文内容项正文内容项正文内容项正文内容项正文内容项正文</p>","rotate":0,"defaultFontName":"","defaultColor":"#333","vertical":false,"groupId":"J0BVEQOTet","textType":"item"}],"background":{"type":"solid","color":"#fff"},"type":"content"},{"id":"l9suGS9T0w","elements":[{"type":"text","id":"X47kOol97s","left":124.51281138790031,"top":32.950307680901545,"width":832.3871886120996,"height":56,"content":"<p style=\"text-align: right;\"><span style=\"font-size: 36px;\">模板内容页标题</span></p>","rotate":0,"defaultFontName":"","defaultColor":"#333","vertical":false,"lineHeight":1,"textType":"title"},{"type":"shape","id":"AK5x6xt_uA","left":42.1,"top":29.950307680901542,"width":70,"height":70,"viewBox":[200,200],"path":"M 0 0 L 200 0 L 200 200 L 0 200 Z","fill":"rgb(155, 0, 0)","fixedRatio":false,"rotate":0,"lock":true},{"type":"line","id":"p7Q_8fzHjx","left":42.08950548635823,"top":100.1,"start":[0,0],"end":[904.5077105575326,0],"points":["",""],"color":"rgb(155, 0, 0)","style":"solid","width":2,"lock":true},{"type":"shape","id":"_G5LMxdY6U","left":53.75,"top":42.25030768090154,"width":46.7,"height":46.7,"viewBox":[200,200],"path":"M 0 0 L 80 0 L 200 100 L 80 200 L 0 200 L 120 100 L 0 0 Z","fill":"#ffffff","fixedRatio":false,"rotate":0,"lock":true},{"type":"shape","id":"vsYExAPImC","left":162.60000000000008,"top":190.7128113879004,"width":60,"height":60,"viewBox":[200,200],"path":"M 0 0 L 200 0 L 200 200 L 0 200 Z","fill":"rgb(155, 0, 0)","fixedRatio":true,"rotate":0,"text":{"content":"<p style=\"text-align: center;\"><strong><span style=\"font-size: 24px;\"><span style=\"color: rgb(255, 255, 255);\">01</span></span></strong></p>","defaultFontName":"","defaultColor":"#000","align":"middle","type":"itemNumber"},"groupId":"XPGPINpoi2"},{"type":"text","id":"En04bAoZAO","left":42.60000000000006,"top":255.9215895610913,"width":300,"height":53,"content":"<p style=\"text-align: center;\"><strong><span style=\"font-size: 22px;\">内容项标题</span></strong></p>","rotate":0,"defaultFontName":"","defaultColor":"#333","vertical":false,"groupId":"XPGPINpoi2","textType":"itemTitle"},{"type":"text","id":"-cTMc-bsZQ","left":42.1,"top":308.9215895610913,"width":300,"height":116,"content":"<p style=\"text-align: center;\">内容项正文内容项正文内容项正文内容项正文内容项正文内容项正文内容项正文内容项正文内容项正文内容项正文内容项正文</p>","rotate":0,"defaultFontName":"","defaultColor":"#333","vertical":false,"groupId":"XPGPINpoi2","textType":"item"},{"type":"shape","id":"Vmg5nVhlwP","left":470.00000000000006,"top":190.7128113879004,"width":60,"height":60,"viewBox":[200,200],"path":"M 0 0 L 200 0 L 200 200 L 0 200 Z","fill":"rgb(155, 0, 0)","fixedRatio":true,"rotate":0,"text":{"content":"<p style=\"text-align: center;\"><strong><span style=\"font-size: 24px;\"><span style=\"color: rgb(255, 255, 255);\">02</span></span></strong></p>","defaultFontName":"","defaultColor":"#000","align":"middle","type":"itemNumber"},"groupId":"qAl9PNYpO3"},{"type":"text","id":"lo7dfXQovZ","left":350,"top":255.9215895610914,"width":300,"height":53,"content":"<p style=\"text-align: center;\"><strong><span style=\"font-size: 22px;\">内容项标题</span></strong></p>","rotate":0,"defaultFontName":"","defaultColor":"#333","vertical":false,"groupId":"qAl9PNYpO3","textType":"itemTitle"},{"type":"text","id":"Lr6LFosxXB","left":350.00000000000006,"top":308.9215895610913,"width":300,"height":116,"content":"<p style=\"text-align: center;\">内容项正文内容项正文内容项正文内容项正文内容项正文内容项正文内容项正文内容项正文内容项正文内容项正文内容项正文</p>","rotate":0,"defaultFontName":"","defaultColor":"#333","vertical":false,"groupId":"qAl9PNYpO3","textType":"item"},{"type":"shape","id":"2lwHPKi_Jp","left":777.4000000000001,"top":188.455693950178,"width":60,"height":60,"viewBox":[200,200],"path":"M 0 0 L 200 0 L 200 200 L 0 200 Z","fill":"rgb(155, 0, 0)","fixedRatio":true,"rotate":0,"text":{"content":"<p style=\"text-align: center;\"><strong><span style=\"font-size: 24px;\"><span style=\"color: rgb(255, 255, 255);\">03</span></span></strong></p>","defaultFontName":"","defaultColor":"#000","align":"middle","type":"itemNumber"},"groupId":"2Eoggzu1EI"},{"type":"text","id":"mSsr6YzCpr","left":657.3999999999999,"top":253.66447212336905,"width":300,"height":53,"content":"<p style=\"text-align: center;\"><strong><span style=\"font-size: 22px;\">内容项标题</span></strong></p>","rotate":0,"defaultFontName":"","defaultColor":"#333","vertical":false,"groupId":"2Eoggzu1EI","textType":"itemTitle"},{"type":"text","id":"ihehnecr_S","left":656.9,"top":308.9215895610913,"width":300,"height":116,"content":"<p style=\"text-align: center;\">内容项正文内容项正文内容项正文内容项正文内容项正文内容项正文内容项正文内容项正文内容项正文内容项正文内容项正文</p>","rotate":0,"defaultFontName":"","defaultColor":"#333","vertical":false,"groupId":"2Eoggzu1EI","textType":"item"}],"background":{"type":"solid","color":"#fff"},"type":"content"},{"id":"CI-9GGV870","elements":[{"type":"text","id":"7mCd12vwX1","left":124.51281138790031,"top":32.950307680901545,"width":832.3871886120996,"height":56,"content":"<p style=\"text-align: right;\"><span style=\"font-size: 36px;\">模板内容页标题</span></p>","rotate":0,"defaultFontName":"","defaultColor":"#333","vertical":false,"lineHeight":1,"textType":"title"},{"type":"shape","id":"3kdbcL92R9","left":42.1,"top":29.950307680901542,"width":70,"height":70,"viewBox":[200,200],"path":"M 0 0 L 200 0 L 200 200 L 0 200 Z","fill":"rgb(155, 0, 0)","fixedRatio":false,"rotate":0,"lock":true},{"type":"line","id":"ZiBrajr-FK","left":42.08950548635823,"top":100.1,"start":[0,0],"end":[904.5077105575326,0],"points":["",""],"color":"rgb(155, 0, 0)","style":"solid","width":2,"lock":true},{"type":"shape","id":"0osXUTkrBj","left":53.75,"top":42.25030768090154,"width":46.7,"height":46.7,"viewBox":[200,200],"path":"M 0 0 L 80 0 L 200 100 L 80 200 L 0 200 L 120 100 L 0 0 Z","fill":"#ffffff","fixedRatio":false,"rotate":0,"lock":true},{"type":"shape","id":"yfgHjk8uJk","left":110,"top":194.41981020166077,"width":60,"height":60,"viewBox":[200,200],"path":"M 0 0 L 200 0 L 200 200 L 0 200 Z","fill":"rgb(155, 0, 0)","fixedRatio":true,"rotate":0,"text":{"content":"<p style=\"text-align: center;\"><strong><span style=\"font-size: 24px;\"><span style=\"color: rgb(255, 255, 255);\">01</span></span></strong></p>","defaultFontName":"","defaultColor":"#000","align":"middle","type":"itemNumber"},"groupId":"rLFQqKgKXU"},{"type":"text","id":"dYxqN1zGxh","left":20,"top":259.6069988137604,"width":240,"height":50,"content":"<p style=\"text-align: center;\"><strong><span style=\"font-size: 20px;\">内容项标题</span></strong></p>","rotate":0,"defaultFontName":"","defaultColor":"#333","vertical":false,"groupId":"rLFQqKgKXU","textType":"itemTitle"},{"type":"text","id":"UHnyhPP5n2","left":20,"top":309.6069988137603,"width":240,"height":140,"content":"<p style=\"text-align: center;\">内容项正文内容项正文内容项正文内容项正文内容项正文内容项正文内容项正文内容项正文内容项正文内容项正文内容项正文</p>","rotate":0,"defaultFontName":"","defaultColor":"#333","vertical":false,"groupId":"rLFQqKgKXU","textType":"item"},{"type":"shape","id":"wdwhVy3FGw","left":350,"top":194.41981020166077,"width":60,"height":60,"viewBox":[200,200],"path":"M 0 0 L 200 0 L 200 200 L 0 200 Z","fill":"rgb(155, 0, 0)","fixedRatio":true,"rotate":0,"text":{"content":"<p style=\"text-align: center;\"><strong><span style=\"font-size: 24px;\"><span style=\"color: rgb(255, 255, 255);\">02</span></span></strong></p>","defaultFontName":"","defaultColor":"#000","align":"middle","type":"itemNumber"},"groupId":"m4OnVg6P2u"},{"type":"text","id":"5jzw4XLVgF","left":260,"top":259.6069988137605,"width":240,"height":50,"content":"<p style=\"text-align: center;\"><strong><span style=\"font-size: 20px;\">内容项标题</span></strong></p>","rotate":0,"defaultFontName":"","defaultColor":"#333","vertical":false,"groupId":"m4OnVg6P2u","textType":"itemTitle"},{"type":"text","id":"VqXn6HBh-m","left":260,"top":309.6069988137604,"width":240,"height":140,"content":"<p style=\"text-align: center;\">内容项正文内容项正文内容项正文内容项正文内容项正文内容项正文内容项正文内容项正文内容项正文内容项正文内容项正文</p>","rotate":0,"defaultFontName":"","defaultColor":"#333","vertical":false,"groupId":"m4OnVg6P2u","textType":"item"},{"type":"shape","id":"QliI3LLJkQ","left":590,"top":194.41981020166077,"width":60,"height":60,"viewBox":[200,200],"path":"M 0 0 L 200 0 L 200 200 L 0 200 Z","fill":"rgb(155, 0, 0)","fixedRatio":true,"rotate":0,"text":{"content":"<p style=\"text-align: center;\"><strong><span style=\"font-size: 24px;\"><span style=\"color: rgb(255, 255, 255);\">03</span></span></strong></p>","defaultFontName":"","defaultColor":"#000","align":"middle","type":"itemNumber"},"groupId":"AE1x15BHF6"},{"type":"text","id":"yABWLD03UV","left":500,"top":259.6069988137605,"width":240,"height":50,"content":"<p style=\"text-align: center;\"><strong><span style=\"font-size: 20px;\">内容项标题</span></strong></p>","rotate":0,"defaultFontName":"","defaultColor":"#333","vertical":false,"groupId":"AE1x15BHF6","textType":"itemTitle"},{"type":"text","id":"xUpuSBIot0","left":500,"top":309.6069988137604,"width":240,"height":140,"content":"<p style=\"text-align: center;\">内容项正文内容项正文内容项正文内容项正文内容项正文内容项正文内容项正文内容项正文内容项正文内容项正文内容项正文</p>","rotate":0,"defaultFontName":"","defaultColor":"#333","vertical":false,"groupId":"AE1x15BHF6","textType":"item"},{"type":"shape","id":"KbFu99PXyv","left":830,"top":194.41981020166077,"width":60,"height":60,"viewBox":[200,200],"path":"M 0 0 L 200 0 L 200 200 L 0 200 Z","fill":"rgb(155, 0, 0)","fixedRatio":true,"rotate":0,"text":{"content":"<p style=\"text-align: center;\"><strong><span style=\"font-size: 24px;\"><span style=\"color: rgb(255, 255, 255);\">04</span></span></strong></p>","defaultFontName":"","defaultColor":"#000","align":"middle","type":"itemNumber"},"groupId":"eUw9k25hy4"},{"type":"text","id":"bX2uO1Ism2","left":740,"top":259.60699881376075,"width":240,"height":50,"content":"<p style=\"text-align: center;\"><strong><span style=\"font-size: 20px;\">内容项标题</span></strong></p>","rotate":0,"defaultFontName":"","defaultColor":"#333","vertical":false,"groupId":"eUw9k25hy4","textType":"itemTitle"},{"type":"text","id":"FgRAbOc5uH","left":740,"top":309.60699881376064,"width":240,"height":140,"content":"<p style=\"text-align: center;\">内容项正文内容项正文内容项正文内容项正文内容项正文内容项正文内容项正文内容项正文内容项正文内容项正文内容项正文</p>","rotate":0,"defaultFontName":"","defaultColor":"#333","vertical":false,"groupId":"eUw9k25hy4","textType":"item"}],"background":{"type":"solid","color":"#fff"},"type":"content"},{"id":"Htu2RJRxw1","elements":[{"type":"image","id":"p6pJ9n6glh","src":"https://images.pexels.com/photos/620337/pexels-photo-620337.jpeg?auto=compress&cs=tinysrgb&w=600","width":1000,"height":344.1577698695136,"left":0,"top":111.57580071174377,"fixedRatio":true,"rotate":0,"filters":{"grayscale":"100%"},"clip":{"shape":"rect","range":[[0,29.842931937172775],[100,82.19895287958116]]},"lock":false,"imageType":"pageFigure"},{"type":"shape","id":"7jVwfMR3D3","left":0,"top":111.57580071174377,"width":1000,"height":344.0241992882562,"viewBox":[200,200],"path":"M 0 0 L 200 0 L 200 200 L 0 200 Z","fill":"rgb(155, 0, 0)","fixedRatio":false,"rotate":0,"lock":true,"opacity":0.8},{"type":"text","id":"eFdW3K4_ZM","left":14.485527876631055,"top":30.726108392645315,"width":971.0289442467379,"height":56,"content":"<p style=\"\"><span style=\"font-size: 36px;\">模板内容页标题</span></p>","rotate":0,"defaultFontName":"","defaultColor":"#333","vertical":false,"lineHeight":1,"textType":"title"},{"type":"line","id":"NwsAZ4balJ","left":25.20759193357058,"top":95.87580071174376,"start":[0,0],"end":[946.7674970344009,0],"points":["",""],"color":"rgb(155, 0, 0)","style":"solid","width":2,"lock":true},{"type":"text","id":"XI_R1qVU7K","left":113.57740213523128,"top":197.31079478054568,"width":360,"height":56,"content":"<p style=\"text-align: center;\"><strong><span style=\"font-size: 24px;\"><span style=\"color: rgb(255, 255, 255);\">内容项标题</span></span></strong></p>","rotate":0,"defaultFontName":"","defaultColor":"#333","vertical":false,"groupId":"y76o4T1LWv","textType":"itemTitle"},{"type":"text","id":"uAakaDze3U","left":148.5774021352313,"top":253.3510083036773,"width":290,"height":140,"content":"<p style=\"text-align: center;\"><span style=\"color: rgb(255, 255, 255);\">内容项正文内容项正文内容项正文内容项正文内容项正文内容项正文内容项正文内容项正文内容项正文内容项正文内容项正文内容项正文内容项正文内容项正文</span></p>","rotate":0,"defaultFontName":"","defaultColor":"#333","vertical":false,"groupId":"y76o4T1LWv","textType":"item"},{"type":"text","id":"slG3krK1lP","left":526.4225978647687,"top":197.31079478054568,"width":360,"height":56,"content":"<p style=\"text-align: center;\" class=\"ProseMirror-selectednode\" draggable=\"true\"><strong><span style=\"font-size: 24px;\"><span style=\"color: #ffffff;\">内容项标题</span></span></strong></p>","rotate":0,"defaultFontName":"","defaultColor":"#333","vertical":false,"groupId":"P3KDXeos6E","textType":"itemTitle"},{"type":"text","id":"NuPKTn9k-3","left":561.4225978647687,"top":253.3510083036773,"width":290,"height":140,"content":"<p style=\"text-align: center;\"><span style=\"color: rgb(255, 255, 255);\">内容项正文内容项正文内容项正文内容项正文内容项正文内容项正文内容项正文内容项正文内容项正文内容项正文内容项正文内容项正文内容项正文内容项正文</span></p>","rotate":0,"defaultFontName":"","defaultColor":"#333","vertical":false,"groupId":"P3KDXeos6E","textType":"item"},{"type":"shape","id":"CIQgwFKp_w","left":900.5269869513642,"top":475.75622775800707,"width":20,"height":20,"viewBox":[200,200],"path":"M 100 0 A 50 50 0 1 1 100 200 A 50 50 0 1 1 100 0 Z","fill":"rgb(155, 0, 0)","fixedRatio":false,"rotate":0,"lock":true},{"type":"shape","id":"j3CuQZkUl5","left":929.8033807829182,"top":475.75622775800707,"width":20,"height":20,"viewBox":[200,200],"path":"M 100 0 A 50 50 0 1 1 100 200 A 50 50 0 1 1 100 0 Z","fill":"rgb(155, 0, 0)","fixedRatio":false,"rotate":0,"lock":true},{"type":"shape","id":"khmpwIGhVn","left":959.0797746144723,"top":475.75622775800707,"width":20,"height":20,"viewBox":[200,200],"path":"M 100 0 A 50 50 0 1 1 100 200 A 50 50 0 1 1 100 0 Z","fill":"rgb(155, 0, 0)","fixedRatio":false,"rotate":0,"lock":true}],"background":{"type":"solid","color":"#fff"},"type":"content"},{"id":"FEpT39jjGV","elements":[{"type":"image","id":"_nBXsgulr1","src":"https://images.pexels.com/photos/620337/pexels-photo-620337.jpeg?auto=compress&cs=tinysrgb&w=600","width":1000,"height":344.1577698695136,"left":0,"top":111.57580071174377,"fixedRatio":true,"rotate":0,"filters":{"grayscale":"100%"},"clip":{"shape":"rect","range":[[0,29.842931937172775],[100,82.19895287958116]]},"lock":false,"imageType":"pageFigure"},{"type":"shape","id":"lNI1CV-1_e","left":0,"top":111.57580071174377,"width":1000,"height":344.0241992882562,"viewBox":[200,200],"path":"M 0 0 L 200 0 L 200 200 L 0 200 Z","fill":"rgb(155, 0, 0)","fixedRatio":false,"rotate":0,"lock":true,"opacity":0.8},{"type":"text","id":"vNGrSIoEyv","left":14.485527876631055,"top":30.726108392645315,"width":971.0289442467379,"height":56,"content":"<p style=\"\"><span style=\"font-size: 36px;\">模板内容页标题</span></p>","rotate":0,"defaultFontName":"","defaultColor":"#333","vertical":false,"lineHeight":1,"textType":"title"},{"type":"line","id":"Jxm2DAQ_bC","left":25.20759193357058,"top":95.87580071174376,"start":[0,0],"end":[946.7674970344009,0],"points":["",""],"color":"rgb(155, 0, 0)","style":"solid","width":2,"lock":true},{"type":"text","id":"HJF1h21pcs","left":20.28146500593124,"top":197.31079478054568,"width":320,"height":50,"content":"<p style=\"text-align: center;\"><strong><span style=\"font-size: 20px;\"><span style=\"color: rgb(255, 255, 255);\">内容项标题</span></span></strong></p>","rotate":0,"defaultFontName":"","defaultColor":"#333","vertical":false,"groupId":"pYtUD8KY0Z","textType":"itemTitle"},{"type":"text","id":"fq-B-Wiqcg","left":35.28146500593124,"top":253.3510083036773,"width":290,"height":140,"content":"<p style=\"text-align: center;\"><span style=\"color: rgb(255, 255, 255);\">内容项正文内容项正文内容项正文内容项正文内容项正文内容项正文内容项正文内容项正文内容项正文内容项正文内容项正文内容项正文内容项正文内容项正文</span></p>","rotate":0,"defaultFontName":"","defaultColor":"#333","vertical":false,"groupId":"pYtUD8KY0Z","textType":"item"},{"type":"shape","id":"r9gLWJedXP","left":900.5269869513642,"top":475.75622775800707,"width":20,"height":20,"viewBox":[200,200],"path":"M 100 0 A 50 50 0 1 1 100 200 A 50 50 0 1 1 100 0 Z","fill":"rgb(155, 0, 0)","fixedRatio":false,"rotate":0,"lock":true},{"type":"shape","id":"t9KkzYs3Rz","left":929.8033807829182,"top":475.75622775800707,"width":20,"height":20,"viewBox":[200,200],"path":"M 100 0 A 50 50 0 1 1 100 200 A 50 50 0 1 1 100 0 Z","fill":"rgb(155, 0, 0)","fixedRatio":false,"rotate":0,"lock":true},{"type":"shape","id":"kQotFV3A-D","left":959.0797746144723,"top":475.75622775800707,"width":20,"height":20,"viewBox":[200,200],"path":"M 100 0 A 50 50 0 1 1 100 200 A 50 50 0 1 1 100 0 Z","fill":"rgb(155, 0, 0)","fixedRatio":false,"rotate":0,"lock":true},{"type":"text","id":"f9vtkbPo_s","left":340.00000000000006,"top":197.31079478054568,"width":320,"height":50,"content":"<p style=\"text-align: center;\"><strong><span style=\"font-size: 20px;\"><span style=\"color: rgb(255, 255, 255);\">内容项标题</span></span></strong></p>","rotate":0,"defaultFontName":"","defaultColor":"#333","vertical":false,"groupId":"gU1sS2bwh_","textType":"itemTitle"},{"type":"text","id":"rhxh7G0Fbh","left":355.00000000000006,"top":253.3510083036773,"width":290,"height":140,"content":"<p style=\"text-align: center;\"><span style=\"color: rgb(255, 255, 255);\">内容项正文内容项正文内容项正文内容项正文内容项正文内容项正文内容项正文内容项正文内容项正文内容项正文内容项正文内容项正文内容项正文内容项正文</span></p>","rotate":0,"defaultFontName":"","defaultColor":"#333","vertical":false,"groupId":"gU1sS2bwh_","textType":"item"},{"type":"text","id":"1JRHs9kzgM","left":659.7185349940687,"top":197.31079478054568,"width":320,"height":50,"content":"<p style=\"text-align: center;\"><strong><span style=\"font-size: 20px;\"><span style=\"color: rgb(255, 255, 255);\">内容项标题</span></span></strong></p>","rotate":0,"defaultFontName":"","defaultColor":"#333","vertical":false,"groupId":"ZammwNMv7u","textType":"itemTitle"},{"type":"text","id":"HarSQWNDfb","left":674.7185349940687,"top":253.3510083036773,"width":290,"height":140,"content":"<p style=\"text-align: center;\"><span style=\"color: rgb(255, 255, 255);\">内容项正文内容项正文内容项正文内容项正文内容项正文内容项正文内容项正文内容项正文内容项正文内容项正文内容项正文内容项正文内容项正文内容项正文</span></p>","rotate":0,"defaultFontName":"","defaultColor":"#333","vertical":false,"groupId":"ZammwNMv7u","textType":"item"}],"background":{"type":"solid","color":"#fff"},"type":"content"},{"id":"QfonksVFv5","elements":[{"type":"image","id":"DDho8zIdN8","src":"https://images.pexels.com/photos/620337/pexels-photo-620337.jpeg?auto=compress&cs=tinysrgb&w=600","width":1000,"height":344.1577698695136,"left":0,"top":111.57580071174377,"fixedRatio":true,"rotate":0,"filters":{"grayscale":"100%"},"clip":{"shape":"rect","range":[[0,29.842931937172775],[100,82.19895287958116]]},"lock":false,"imageType":"pageFigure"},{"type":"shape","id":"-WypBFQB9i","left":0,"top":111.57580071174377,"width":1000,"height":344.0241992882562,"viewBox":[200,200],"path":"M 0 0 L 200 0 L 200 200 L 0 200 Z","fill":"rgb(155, 0, 0)","fixedRatio":false,"rotate":0,"lock":true,"opacity":0.8},{"type":"text","id":"iPL5Su83-U","left":14.485527876631055,"top":30.726108392645315,"width":971.0289442467379,"height":56,"content":"<p style=\"\"><span style=\"font-size: 36px;\">模板内容页标题</span></p>","rotate":0,"defaultFontName":"","defaultColor":"#333","vertical":false,"lineHeight":1,"textType":"title"},{"type":"line","id":"MT-3mo5dJK","left":25.20759193357058,"top":95.87580071174376,"start":[0,0],"end":[946.7674970344009,0],"points":["",""],"color":"rgb(155, 0, 0)","style":"solid","width":2,"lock":true},{"type":"text","id":"9t1Et2cEhC","left":14.485527876631055,"top":196.5693950177936,"width":240,"height":47,"content":"<p style=\"text-align: center;\" class=\"\"><strong><span style=\"font-size: 18px;\"><span style=\"color: rgb(255, 255, 255);\">内容项标题</span></span></strong></p>","rotate":0,"defaultFontName":"","defaultColor":"#333","vertical":false,"groupId":"CaeuxQ2ET8","textType":"itemTitle"},{"type":"text","id":"DpL-CmhS5Q","left":14.485527876631055,"top":243.55860023724793,"width":240,"height":140,"content":"<p style=\"text-align: center;\" class=\"\"><span style=\"color: rgb(255, 255, 255);\">内容项正文内容项正文内容项正文内容项正文内容项正文内容项正文内容项正文内容项正文内容项正文内容项正文内容项正文内容项正文</span></p>","rotate":0,"defaultFontName":"","defaultColor":"#333","vertical":false,"groupId":"CaeuxQ2ET8","textType":"item"},{"type":"shape","id":"hyyXuCRbb6","left":900.5269869513642,"top":475.75622775800707,"width":20,"height":20,"viewBox":[200,200],"path":"M 100 0 A 50 50 0 1 1 100 200 A 50 50 0 1 1 100 0 Z","fill":"rgb(155, 0, 0)","fixedRatio":false,"rotate":0,"lock":true},{"type":"shape","id":"1u8xooh-9P","left":929.8033807829182,"top":475.75622775800707,"width":20,"height":20,"viewBox":[200,200],"path":"M 100 0 A 50 50 0 1 1 100 200 A 50 50 0 1 1 100 0 Z","fill":"rgb(155, 0, 0)","fixedRatio":false,"rotate":0,"lock":true},{"type":"shape","id":"xf6snMUoFX","left":959.0797746144723,"top":475.75622775800707,"width":20,"height":20,"viewBox":[200,200],"path":"M 100 0 A 50 50 0 1 1 100 200 A 50 50 0 1 1 100 0 Z","fill":"rgb(155, 0, 0)","fixedRatio":false,"rotate":0,"lock":true},{"type":"text","id":"lbRxArLbnQ","left":258.16184262554367,"top":196.5693950177936,"width":240,"height":47,"content":"<p style=\"text-align: center;\" class=\"\"><strong><span style=\"font-size: 18px;\"><span style=\"color: rgb(255, 255, 255);\">内容项标题</span></span></strong></p>","rotate":0,"defaultFontName":"","defaultColor":"#333","vertical":false,"groupId":"wPRHQmeUiL","textType":"itemTitle"},{"type":"text","id":"-QeOKlXUwi","left":258.16184262554367,"top":243.55860023724793,"width":240,"height":140,"content":"<p style=\"text-align: center;\" class=\"\"><span style=\"color: rgb(255, 255, 255);\">内容项正文内容项正文内容项正文内容项正文内容项正文内容项正文内容项正文内容项正文内容项正文内容项正文内容项正文内容项正文</span></p>","rotate":0,"defaultFontName":"","defaultColor":"#333","vertical":false,"groupId":"wPRHQmeUiL","textType":"item"},{"type":"text","id":"a2YhXPzTmW","left":501.8381573744563,"top":196.5693950177936,"width":240,"height":47,"content":"<p style=\"text-align: center;\" class=\"\"><strong><span style=\"font-size: 18px;\"><span style=\"color: rgb(255, 255, 255);\">内容项标题</span></span></strong></p>","rotate":0,"defaultFontName":"","defaultColor":"#333","vertical":false,"groupId":"mSAS60BuNF","textType":"itemTitle"},{"type":"text","id":"cqGMVD7lvO","left":501.8381573744563,"top":243.55860023724793,"width":240,"height":140,"content":"<p style=\"text-align: center;\" class=\"\"><span style=\"color: rgb(255, 255, 255);\">内容项正文内容项正文内容项正文内容项正文内容项正文内容项正文内容项正文内容项正文内容项正文内容项正文内容项正文内容项正文</span></p>","rotate":0,"defaultFontName":"","defaultColor":"#333","vertical":false,"groupId":"mSAS60BuNF","textType":"item"},{"type":"text","id":"TGCsJsOare","left":745.5144721233689,"top":196.5693950177936,"width":240,"height":47,"content":"<p style=\"text-align: center;\" class=\"\"><strong><span style=\"font-size: 18px;\"><span style=\"color: rgb(255, 255, 255);\">内容项标题</span></span></strong></p>","rotate":0,"defaultFontName":"","defaultColor":"#333","vertical":false,"groupId":"IVno5JZaPA","textType":"itemTitle"},{"type":"text","id":"jAd4rkauq8","left":745.5144721233689,"top":243.55860023724793,"width":240,"height":140,"content":"<p style=\"text-align: center;\" class=\"\"><span style=\"color: rgb(255, 255, 255);\">内容项正文内容项正文内容项正文内容项正文内容项正文内容项正文内容项正文内容项正文内容项正文内容项正文内容项正文内容项正文</span></p>","rotate":0,"defaultFontName":"","defaultColor":"#333","vertical":false,"groupId":"IVno5JZaPA","textType":"item"}],"background":{"type":"solid","color":"#fff"},"type":"content"},{"id":"uLaMS1nhGV","elements":[{"type":"line","id":"or3TzqC6fQ","left":753.929418742586,"top":552.9455627224199,"start":[0,0],"end":[257.26571767497035,0],"points":["",""],"color":"rgb(155, 0, 0)","style":"dotted","width":20,"lock":true},{"type":"line","id":"SNeLsEowLs","left":0,"top":553.0487655693951,"start":[0,0],"end":[779.9525504151839,0],"points":["",""],"color":"rgb(155, 0, 0)","style":"solid","width":20,"lock":true},{"type":"shape","id":"OJKQ6P3Jjd","left":0,"top":144.5,"width":1000,"height":295.1,"viewBox":[200,200],"path":"M 0 0 L 200 0 L 200 200 L 0 200 Z","fill":"rgb(155, 0, 0)","fixedRatio":false,"rotate":0,"lock":true},{"type":"shape","id":"6FlhrwIw6G","left":93.1613285883749,"top":172.6846381969158,"width":383.3036773428233,"height":238.73072360616845,"viewBox":[383.3036773428233,238.73072360616845],"path":"M 29.841340450771057 0 L 383.3036773428233 0 L 383.3036773428233 208.8893831553974 Q 383.3036773428233 238.73072360616845 353.46233689205224 238.73072360616845 L 0 238.73072360616845 L 0 29.841340450771057 Q 0 0 29.841340450771057 0 Z","fill":"#ffffff","fixedRatio":false,"rotate":0,"pathFormula":"roundRectDiagonal","keypoints":[0.125],"shadow":{"h":1,"v":1,"blur":2,"color":"rgba(108, 107, 107, 0.36)"},"groupId":"jOGqKSa3j6"},{"type":"text","id":"yLGFrIe8Ho","left":134.81316725978658,"top":248.0002965599051,"width":300,"height":50,"content":"<p style=\"text-align: center;\"><strong><span style=\"font-size: 20px;\">内容项标题</span></strong></p>","rotate":0,"defaultFontName":"","defaultColor":"#333","vertical":false,"groupId":"jOGqKSa3j6","textType":"itemTitle"},{"type":"text","id":"6XawevAyQp","left":134.81316725978655,"top":289.43979833926454,"width":300,"height":116,"content":"<p style=\"text-align: center;\">内容项正文内容项正文内容项正文内容项正文内容项正文内容项正文内容项正文内容项正文内容项正文内容项正文内容项正文内容项正文</p>","rotate":0,"defaultFontName":"","defaultColor":"#333","vertical":false,"groupId":"jOGqKSa3j6","textType":"item"},{"type":"image","id":"xqeLTuBOBI","src":"https://images.pexels.com/photos/29928161/pexels-photo-29928161.jpeg?auto=compress&cs=tinysrgb&w=600","width":60,"height":60,"left":254.81316725978658,"top":186.0002965599051,"fixedRatio":true,"rotate":0,"clip":{"shape":"ellipse","range":[[0,0],[100,100]]},"filters":{"grayscale":"100%"},"groupId":"jOGqKSa3j6","shadow":{"h":2,"v":2,"blur":4,"color":"#808080"},"imageType":"itemFigure"},{"type":"shape","id":"3Id4yJ7r5J","left":523.534994068802,"top":166.7090747330961,"width":383.3036773428233,"height":238.73072360616845,"viewBox":[383.3036773428233,238.73072360616845],"path":"M 29.841340450771057 0 L 383.3036773428233 0 L 383.3036773428233 208.8893831553974 Q 383.3036773428233 238.73072360616845 353.46233689205224 238.73072360616845 L 0 238.73072360616845 L 0 29.841340450771057 Q 0 0 29.841340450771057 0 Z","fill":"#ffffff","fixedRatio":false,"rotate":0,"pathFormula":"roundRectDiagonal","keypoints":[0.125],"shadow":{"h":1,"v":1,"blur":2,"color":"rgba(108, 107, 107, 0.36)"},"groupId":"uphwWsEh3h"},{"type":"text","id":"EsZvXertnu","left":565.1868327402135,"top":242.0247330960854,"width":300,"height":50,"content":"<p style=\"text-align: center;\"><strong><span style=\"font-size: 20px;\">内容项标题</span></strong></p>","rotate":0,"defaultFontName":"","defaultColor":"#333","vertical":false,"groupId":"uphwWsEh3h","textType":"itemTitle"},{"type":"text","id":"CtcNjvAa62","left":565.1868327402135,"top":283.4642348754446,"width":300,"height":116,"content":"<p style=\"text-align: center;\">内容项正文内容项正文内容项正文内容项正文内容项正文内容项正文内容项正文内容项正文内容项正文内容项正文内容项正文内容项正文</p>","rotate":0,"defaultFontName":"","defaultColor":"#333","vertical":false,"groupId":"uphwWsEh3h","textType":"item"},{"type":"image","id":"XDRK55EqpP","src":"https://images.pexels.com/photos/29928161/pexels-photo-29928161.jpeg?auto=compress&cs=tinysrgb&w=600","width":60,"height":60,"left":685.1868327402133,"top":180.02473309608538,"fixedRatio":true,"rotate":0,"clip":{"shape":"ellipse","range":[[0,0],[100,100]]},"filters":{"grayscale":"100%"},"groupId":"uphwWsEh3h","shadow":{"h":2,"v":2,"blur":4,"color":"#808080"},"imageType":"itemFigure"},{"type":"text","id":"prsX7b5KHn","left":66.28577253855278,"top":52.22670151245551,"width":919.2286995848161,"height":56,"content":"<p style=\"\"><span style=\"font-size: 36px;\">模板内容页标题</span></p>","rotate":0,"defaultFontName":"","defaultColor":"#333","vertical":false,"lineHeight":1,"textType":"title"},{"type":"shape","id":"tbSj6_rn3k","left":18.8,"top":60.2,"width":40,"height":40,"viewBox":[200,200],"path":"M 0 0 L 80 0 L 200 100 L 80 200 L 0 200 L 120 100 L 0 0 Z","fill":"rgb(155, 0, 0)","fixedRatio":true,"rotate":0,"lock":true}],"background":{"type":"solid","color":"#fff"},"type":"content"},{"id":"MSvLMvl3uD","elements":[{"type":"line","id":"smX2eqG7qN","left":753.929418742586,"top":552.9455627224199,"start":[0,0],"end":[257.26571767497035,0],"points":["",""],"color":"rgb(155, 0, 0)","style":"dotted","width":20,"lock":true},{"type":"line","id":"qGfaD2aRGg","left":0,"top":553.0487655693951,"start":[0,0],"end":[779.9525504151839,0],"points":["",""],"color":"rgb(155, 0, 0)","style":"solid","width":20,"lock":true},{"type":"shape","id":"tSeArUmT9c","left":0,"top":144.5,"width":1000,"height":295.1,"viewBox":[200,200],"path":"M 0 0 L 200 0 L 200 200 L 0 200 Z","fill":"rgb(155, 0, 0)","fixedRatio":false,"rotate":0,"lock":true},{"type":"shape","id":"g65cIoDVng","left":30.006053529062875,"top":172.70000000000005,"width":300,"height":238.7,"viewBox":[300,238.7],"path":"M 29.8375 0 L 300 0 L 300 208.86249999999998 Q 300 238.7 270.1625 238.7 L 0 238.7 L 0 29.8375 Q 0 0 29.8375 0 Z","fill":"#ffffff","fixedRatio":false,"rotate":0,"pathFormula":"roundRectDiagonal","keypoints":[0.125],"shadow":{"h":1,"v":1,"blur":2,"color":"rgba(108, 107, 107, 0.36)"},"groupId":"RNnJ1blc-z"},{"type":"text","id":"84Cmlnx9bk","left":40.00605352906286,"top":248.01536180308423,"width":280,"height":50,"content":"<p style=\"text-align: center;\"><strong><span style=\"font-size: 20px;\">内容项标题</span></strong></p>","rotate":0,"defaultFontName":"","defaultColor":"#333","vertical":false,"groupId":"RNnJ1blc-z","textType":"itemTitle"},{"type":"text","id":"2iRWJ5YSuk","left":40.00605352906286,"top":289.4153618030841,"width":280,"height":116,"content":"<p style=\"text-align: center;\">内容项正文内容项正文内容项正文内容项正文内容项正文内容项正文内容项正文内容项正文内容项正文内容项正文内容项正文内容项正文</p>","rotate":0,"defaultFontName":"","defaultColor":"#333","vertical":false,"groupId":"RNnJ1blc-z","textType":"item"},{"type":"image","id":"05JlO5pTp3","src":"https://images.pexels.com/photos/29928161/pexels-photo-29928161.jpeg?auto=compress&cs=tinysrgb&w=600","width":60,"height":60,"left":150.0060535290628,"top":186.01536180308423,"fixedRatio":true,"rotate":0,"clip":{"shape":"ellipse","range":[[0,0],[100,100]]},"filters":{"grayscale":"100%"},"shadow":{"h":2,"v":2,"blur":4,"color":"#808080"},"groupId":"RNnJ1blc-z","imageType":"itemFigure"},{"type":"text","id":"VA1TtHjLiQ","left":66.28577253855278,"top":52.22670151245551,"width":919.2286995848161,"height":56,"content":"<p style=\"\"><span style=\"font-size: 36px;\">模板内容页标题</span></p>","rotate":0,"defaultFontName":"","defaultColor":"#333","vertical":false,"lineHeight":1,"textType":"title"},{"type":"shape","id":"0TFZm5yUlZ","left":18.8,"top":60.2,"width":40,"height":40,"viewBox":[200,200],"path":"M 0 0 L 80 0 L 200 100 L 80 200 L 0 200 L 120 100 L 0 0 Z","fill":"rgb(155, 0, 0)","fixedRatio":true,"rotate":0,"lock":true},{"type":"shape","id":"7h_tFwlWxS","left":350,"top":172.70000000000005,"width":300,"height":238.7,"viewBox":[300,238.7],"path":"M 29.8375 0 L 300 0 L 300 208.86249999999998 Q 300 238.7 270.1625 238.7 L 0 238.7 L 0 29.8375 Q 0 0 29.8375 0 Z","fill":"#ffffff","fixedRatio":false,"rotate":0,"pathFormula":"roundRectDiagonal","keypoints":[0.125],"shadow":{"h":1,"v":1,"blur":2,"color":"rgba(108, 107, 107, 0.36)"},"groupId":"8UbHbxjY16"},{"type":"text","id":"opyNKT3DAH","left":360,"top":248.0153618030842,"width":280,"height":50,"content":"<p style=\"text-align: center;\"><strong><span style=\"font-size: 20px;\">内容项标题</span></strong></p>","rotate":0,"defaultFontName":"","defaultColor":"#333","vertical":false,"groupId":"8UbHbxjY16","textType":"itemTitle"},{"type":"text","id":"_01S8CxzKp","left":360,"top":289.415361803084,"width":280,"height":116,"content":"<p style=\"text-align: center;\">内容项正文内容项正文内容项正文内容项正文内容项正文内容项正文内容项正文内容项正文内容项正文内容项正文内容项正文内容项正文</p>","rotate":0,"defaultFontName":"","defaultColor":"#333","vertical":false,"groupId":"8UbHbxjY16","textType":"item"},{"type":"image","id":"fiUDiAtG8b","src":"https://images.pexels.com/photos/29928161/pexels-photo-29928161.jpeg?auto=compress&cs=tinysrgb&w=600","width":60,"height":60,"left":470.0000000000001,"top":186.01536180308423,"fixedRatio":true,"rotate":0,"clip":{"shape":"ellipse","range":[[0,0],[100,100]]},"filters":{"grayscale":"100%"},"shadow":{"h":2,"v":2,"blur":4,"color":"#808080"},"groupId":"8UbHbxjY16","imageType":"itemFigure"},{"type":"shape","id":"s_YMf8724H","left":669.9939464709372,"top":172.70000000000002,"width":300,"height":238.7,"viewBox":[300,238.7],"path":"M 29.8375 0 L 300 0 L 300 208.86249999999998 Q 300 238.7 270.1625 238.7 L 0 238.7 L 0 29.8375 Q 0 0 29.8375 0 Z","fill":"#ffffff","fixedRatio":false,"rotate":0,"pathFormula":"roundRectDiagonal","keypoints":[0.125],"shadow":{"h":1,"v":1,"blur":2,"color":"rgba(108, 107, 107, 0.36)"},"groupId":"Ri0R4T0iCO"},{"type":"text","id":"AgtzB8Klnj","left":679.9939464709372,"top":248.01536180308418,"width":280,"height":50,"content":"<p style=\"text-align: center;\"><strong><span style=\"font-size: 20px;\">内容项标题</span></strong></p>","rotate":0,"defaultFontName":"","defaultColor":"#333","vertical":false,"groupId":"Ri0R4T0iCO","textType":"itemTitle"},{"type":"text","id":"sgbQPoRHcn","left":679.9939464709372,"top":289.4153618030841,"width":280,"height":116,"content":"<p style=\"text-align: center;\">内容项正文内容项正文内容项正文内容项正文内容项正文内容项正文内容项正文内容项正文内容项正文内容项正文内容项正文内容项正文</p>","rotate":0,"defaultFontName":"","defaultColor":"#333","vertical":false,"groupId":"Ri0R4T0iCO","textType":"item"},{"type":"image","id":"a3vFMm9c2y","src":"https://images.pexels.com/photos/29928161/pexels-photo-29928161.jpeg?auto=compress&cs=tinysrgb&w=600","width":60,"height":60,"left":789.9939464709372,"top":186.0153618030842,"fixedRatio":true,"rotate":0,"clip":{"shape":"ellipse","range":[[0,0],[100,100]]},"filters":{"grayscale":"100%"},"shadow":{"h":2,"v":2,"blur":4,"color":"#808080"},"groupId":"Ri0R4T0iCO","imageType":"itemFigure"}],"background":{"type":"solid","color":"#fff"},"type":"content"},{"id":"HyxBgK_8HD","elements":[{"type":"line","id":"JZDSxqkgne","left":753.929418742586,"top":552.9455627224199,"start":[0,0],"end":[257.26571767497035,0],"points":["",""],"color":"rgb(155, 0, 0)","style":"dotted","width":20,"lock":true},{"type":"line","id":"GpfJYew-zr","left":0,"top":553.0487655693951,"start":[0,0],"end":[779.9525504151839,0],"points":["",""],"color":"rgb(155, 0, 0)","style":"solid","width":20,"lock":true},{"type":"shape","id":"zwNy7sjU5l","left":20.72046263345199,"top":106.68861209964412,"width":958.559074733096,"height":391.4819691577699,"viewBox":[958.559074733096,391.4819691577699],"path":"M 29.875428483798675 0 L 958.559074733096 0 L 958.559074733096 361.60654067397127 Q 958.559074733096 391.4819691577699 928.6836462492973 391.4819691577699 L 0 391.4819691577699 L 0 29.875428483798675 Q 0 0 29.875428483798675 0 Z","fill":"rgb(155, 0, 0)","fixedRatio":false,"rotate":0,"opacity":1,"pathFormula":"roundRectDiagonal","keypoints":[0.07631367684205827],"lock":true},{"type":"text","id":"8kwpL5AMt0","left":66.35273576512463,"top":24.70831479833926,"width":917.0045002965599,"height":56,"content":"<p style=\"\" class=\"\"><span style=\"font-size: 36px;\">模板内容页标题</span></p>","rotate":0,"defaultFontName":"","defaultColor":"#333","vertical":false,"lineHeight":1,"textType":"title"},{"type":"shape","id":"khLzhRTMuZ","left":20.72046263345199,"top":32.70831479833926,"width":40,"height":40,"viewBox":[200,200],"path":"M 0 0 L 80 0 L 200 100 L 80 200 L 0 200 L 120 100 L 0 0 Z","fill":"rgb(155, 0, 0)","fixedRatio":true,"rotate":0,"lock":true},{"type":"shape","id":"4U0cx1s0Hh","left":30.27580071174369,"top":116.38801897983397,"width":464.5907473309609,"height":181.20717674970336,"viewBox":[464.5907473309609,181.20717674970336],"path":"M 22.65089709371292 0 L 464.5907473309609 0 L 464.5907473309609 158.55627965599044 Q 464.5907473309609 181.20717674970336 441.939850237248 181.20717674970336 L 0 181.20717674970336 L 0 22.65089709371292 Q 0 0 22.65089709371292 0 Z","fill":"#ffffff","fixedRatio":false,"rotate":0,"pathFormula":"roundRectDiagonal","keypoints":[0.125],"shadow":{"h":1,"v":1,"blur":2,"color":"rgba(108, 107, 107, 0.36)"},"groupId":"pLMbasKd03"},{"type":"text","id":"U0MgegYyYZ","left":137.74317912218257,"top":128.20160142348757,"width":337.08778173190984,"height":50,"content":"<p style=\"\"><strong><span style=\"font-size: 20px;\">内容项标题</span></strong></p>","rotate":0,"defaultFontName":"","defaultColor":"#333","vertical":false,"textType":"itemTitle","groupId":"pLMbasKd03"},{"type":"text","id":"SurBFueI5E","left":137.74317912218257,"top":168.52900355871887,"width":337.08778173190984,"height":116,"content":"<p style=\"\">内容项正文内容项正文内容项正文内容项正文内容项正文内容项正文内容项正文内容项正文内容项正文内容项正文内容项正文内容项正文</p>","rotate":0,"defaultFontName":"","defaultColor":"#333","vertical":false,"groupId":"pLMbasKd03","textType":"item"},{"type":"image","id":"-oCVaVViMV","src":"https://images.pexels.com/photos/29968980/pexels-photo-29968980.jpeg?auto=compress&cs=tinysrgb&w=600","width":76.95729537366549,"height":126.55693950177937,"left":51.73368920521935,"top":143.71313760379596,"fixedRatio":true,"rotate":0,"filters":{"grayscale":"100%","opacity":"100%"},"lock":false,"clip":{"shape":"rect","range":[[0,0],[91.74311926605505,100]]},"radius":5,"groupId":"pLMbasKd03","imageType":"itemFigure"},{"type":"shape","id":"4Uj3V6W5Jw","left":505.28884934756815,"top":116.38801897983397,"width":464.5907473309609,"height":181.20717674970336,"viewBox":[464.5907473309609,181.20717674970336],"path":"M 22.65089709371292 0 L 464.5907473309609 0 L 464.5907473309609 158.55627965599044 Q 464.5907473309609 181.20717674970336 441.939850237248 181.20717674970336 L 0 181.20717674970336 L 0 22.65089709371292 Q 0 0 22.65089709371292 0 Z","fill":"#ffffff","fixedRatio":false,"rotate":0,"pathFormula":"roundRectDiagonal","keypoints":[0.125],"shadow":{"h":1,"v":1,"blur":2,"color":"rgba(108, 107, 107, 0.36)"},"groupId":"wiVHgyUmhy"},{"type":"text","id":"YH7Albs6l9","left":612.7562277580071,"top":128.20160142348757,"width":337.08778173190984,"height":50,"content":"<p style=\"\"><strong><span style=\"font-size: 20px;\">内容项标题</span></strong></p>","rotate":0,"defaultFontName":"","defaultColor":"#333","vertical":false,"groupId":"wiVHgyUmhy","textType":"itemTitle"},{"type":"text","id":"mA1JIQ0Qz4","left":612.7562277580071,"top":168.5290035587188,"width":337.08778173190984,"height":116,"content":"<p style=\"\">内容项正文内容项正文内容项正文内容项正文内容项正文内容项正文内容项正文内容项正文内容项正文内容项正文内容项正文内容项正文</p>","rotate":0,"defaultFontName":"","defaultColor":"#333","vertical":false,"groupId":"wiVHgyUmhy","textType":"item"},{"type":"image","id":"ov8077oZJd","src":"https://images.pexels.com/photos/29968980/pexels-photo-29968980.jpeg?auto=compress&cs=tinysrgb&w=600","width":76.95729537366549,"height":126.55693950177937,"left":526.7467378410438,"top":143.7131376037959,"fixedRatio":true,"rotate":0,"filters":{"grayscale":"100%","opacity":"100%"},"lock":false,"clip":{"shape":"rect","range":[[0,0],[91.74311926605505,100]]},"radius":5,"groupId":"wiVHgyUmhy","imageType":"itemFigure"},{"type":"shape","id":"gB-r9m2-or","left":30.27580071174371,"top":307.50729537366544,"width":464.5907473309609,"height":181.20717674970336,"viewBox":[464.5907473309609,181.20717674970336],"path":"M 22.65089709371292 0 L 464.5907473309609 0 L 464.5907473309609 158.55627965599044 Q 464.5907473309609 181.20717674970336 441.939850237248 181.20717674970336 L 0 181.20717674970336 L 0 22.65089709371292 Q 0 0 22.65089709371292 0 Z","fill":"#ffffff","fixedRatio":false,"rotate":0,"pathFormula":"roundRectDiagonal","keypoints":[0.125],"shadow":{"h":1,"v":1,"blur":2,"color":"rgba(108, 107, 107, 0.36)"},"groupId":"co2yFbWSVK"},{"type":"text","id":"uc6ZBbOiPP","left":137.74317912218257,"top":319.320877817319,"width":337.08778173190984,"height":50,"content":"<p style=\"\"><strong><span style=\"font-size: 20px;\">内容项标题</span></strong></p>","rotate":0,"defaultFontName":"","defaultColor":"#333","vertical":false,"groupId":"co2yFbWSVK","textType":"itemTitle"},{"type":"text","id":"d0zrYO_ZER","left":137.74317912218257,"top":359.6482799525503,"width":337.08778173190984,"height":116,"content":"<p style=\"\">内容项正文内容项正文内容项正文内容项正文内容项正文内容项正文内容项正文内容项正文内容项正文内容项正文内容项正文内容项正文</p>","rotate":0,"defaultFontName":"","defaultColor":"#333","vertical":false,"groupId":"co2yFbWSVK","textType":"item"},{"type":"image","id":"ThhG3PDKjV","src":"https://images.pexels.com/photos/29968980/pexels-photo-29968980.jpeg?auto=compress&cs=tinysrgb&w=600","width":76.95729537366549,"height":126.55693950177937,"left":51.73368920521936,"top":334.83241399762744,"fixedRatio":true,"rotate":0,"filters":{"grayscale":"100%","opacity":"100%"},"lock":false,"clip":{"shape":"rect","range":[[0,0],[91.74311926605505,100]]},"radius":5,"groupId":"co2yFbWSVK","imageType":"itemFigure"},{"type":"shape","id":"0vXN0Vd39s","left":505.28884934756843,"top":307.50729537366544,"width":464.5907473309609,"height":181.20717674970336,"viewBox":[464.5907473309609,181.20717674970336],"path":"M 22.65089709371292 0 L 464.5907473309609 0 L 464.5907473309609 158.55627965599044 Q 464.5907473309609 181.20717674970336 441.939850237248 181.20717674970336 L 0 181.20717674970336 L 0 22.65089709371292 Q 0 0 22.65089709371292 0 Z","fill":"#ffffff","fixedRatio":false,"rotate":0,"pathFormula":"roundRectDiagonal","keypoints":[0.125],"shadow":{"h":1,"v":1,"blur":2,"color":"rgba(108, 107, 107, 0.36)"},"groupId":"2RFdgFxzKb"},{"type":"text","id":"ddfv7fCGIq","left":612.7562277580071,"top":319.320877817319,"width":337.08778173190984,"height":50,"content":"<p style=\"\"><strong><span style=\"font-size: 20px;\">内容项标题</span></strong></p>","rotate":0,"defaultFontName":"","defaultColor":"#333","vertical":false,"groupId":"2RFdgFxzKb","textType":"itemTitle"},{"type":"text","id":"fTfdkoezQt","left":612.7562277580071,"top":359.6482799525503,"width":337.08778173190984,"height":116,"content":"<p style=\"\">内容项正文内容项正文内容项正文内容项正文内容项正文内容项正文内容项正文内容项正文内容项正文内容项正文内容项正文内容项正文</p>","rotate":0,"defaultFontName":"","defaultColor":"#333","vertical":false,"groupId":"2RFdgFxzKb","textType":"item"},{"type":"image","id":"vzVOVTS5V3","src":"https://images.pexels.com/photos/29968980/pexels-photo-29968980.jpeg?auto=compress&cs=tinysrgb&w=600","width":76.95729537366549,"height":126.55693950177937,"left":526.7467378410438,"top":334.8324139976273,"fixedRatio":true,"rotate":0,"filters":{"grayscale":"100%","opacity":"100%"},"lock":false,"clip":{"shape":"rect","range":[[0,0],[91.74311926605505,100]]},"radius":5,"groupId":"2RFdgFxzKb","imageType":"itemFigure"}],"background":{"type":"solid","color":"#fff"},"type":"content"},{"id":"5RzzRus0T3","elements":[{"type":"image","id":"28ppOIUtB0","src":"https://images.pexels.com/photos/29968980/pexels-photo-29968980.jpeg?auto=compress&cs=tinysrgb&w=600","width":372.8317223198594,"height":562.5,"left":0,"top":0,"fixedRatio":true,"rotate":0,"lock":true,"radius":0,"filters":{"grayscale":"100%"},"imageType":"pageFigure"},{"type":"text","id":"7FRayOtg_b","left":451.4176786773429,"top":143.26334519572953,"width":510.82443653618026,"height":56,"content":"<p style=\"\"><span style=\"font-size: 36px;\"><span style=\"color: rgb(155, 0, 0);\">模板内容页标题</span></span></p>","rotate":0,"defaultFontName":"","defaultColor":"#333","vertical":false,"lineHeight":1,"paragraphSpace":0,"textType":"title"},{"type":"shape","id":"4e-Zx3_eW9","left":419.4176786773429,"top":155.26334519572953,"width":32,"height":32,"viewBox":[200,200],"path":"M 0 0 L 80 0 L 200 100 L 80 200 L 0 200 L 120 100 L 0 0 Z","fill":"rgb(155, 0, 0)","fixedRatio":true,"rotate":0,"lock":true},{"type":"text","id":"EKEv5ngr8j","left":419.4176786773429,"top":235.25,"width":542.8244365361803,"height":92,"content":"<p style=\"\">内容项正文内容项正文内容项正文内容项正文内容项正文内容项正文内容项正文内容项正文内容项正文内容项正文内容项正文内容项正文内容项正文内容项</p>","rotate":0,"defaultFontName":"","defaultColor":"#333","vertical":false,"textType":"content"},{"type":"line","id":"bwIp7JGbNP","left":419.19205960854094,"top":213.41887233096085,"start":[0,0],"end":[540.4804270462632,0],"points":["",""],"color":"rgb(155, 0, 0)","style":"solid","width":2,"lock":true},{"type":"shape","id":"5JiuPK0Y7m","left":952.2597864768684,"top":11.378540183867166,"width":36.65230204626337,"height":36.65230204626337,"viewBox":[36.65230204626337,36.65230204626337],"path":"M 0 0 L 0 36.65230204626337 L 36.65230204626337 36.65230204626337 L 36.65230204626337 32.98707184163703 L 3.6652302046263374 32.98707184163703 L 3.6652302046263374 0 Z","fill":"rgb(155, 0, 0)","fixedRatio":false,"rotate":180,"pathFormula":"L","keypoints":[0.1],"lock":true},{"type":"shape","id":"h2s2gk4wxE","left":952.2597864768684,"top":513.6679826512456,"width":36.65230204626337,"height":36.65230204626337,"viewBox":[36.65230204626337,36.65230204626337],"path":"M 0 0 L 0 36.65230204626337 L 36.65230204626337 36.65230204626337 L 36.65230204626337 32.98707184163703 L 3.6652302046263374 32.98707184163703 L 3.6652302046263374 0 Z","fill":"rgb(155, 0, 0)","fixedRatio":false,"rotate":-90,"pathFormula":"L","keypoints":[0.1],"lock":true}],"background":{"type":"solid","color":"#fff"},"type":"content"},{"id":"TKqz4TKoya","elements":[{"type":"image","id":"ex8J_yNoJS","src":"https://images.pexels.com/photos/29968980/pexels-photo-29968980.jpeg?auto=compress&cs=tinysrgb&w=600","width":372.8317223198594,"height":562.5,"left":627.1682776801406,"top":0,"fixedRatio":true,"rotate":0,"lock":true,"radius":0,"filters":{"grayscale":"100%"},"imageType":"pageFigure"},{"type":"text","id":"KyKJpgFCKe","left":41.042129169283385,"top":145.2339557820458,"width":510.82443653618026,"height":56,"content":"<p style=\"text-align: right;\"><span style=\"font-size: 36px;\"><span style=\"color: rgb(155, 0, 0);\">模板内容页标题</span></span></p>","rotate":0,"defaultFontName":"","defaultColor":"#333","vertical":false,"lineHeight":1,"paragraphSpace":0,"textType":"title"},{"type":"shape","id":"Ux-sxr9RCH","left":551.8665657054636,"top":157.2339557820458,"width":32,"height":32,"viewBox":[200,200],"path":"M 200 0 L 120 0 L 0 100 L 120 200 L 200 200 L 80 100 L 200 0 Z","fill":"rgb(155, 0, 0)","fixedRatio":true,"rotate":0,"lock":true},{"type":"text","id":"SWvlYkR6yg","left":41.042129169283385,"top":238.00562209981848,"width":542.8244365361803,"height":92,"content":"<p style=\"text-align: right;\">内容项正文内容项正文内容项正文内容项正文内容项正文内容项正文内容项正文内容项正文内容项正文内容项正文内容项正文内容项正文内容项正文内容项</p>","rotate":0,"defaultFontName":"","defaultColor":"#333","vertical":false,"textType":"content"},{"type":"line","id":"ZVCQAicdyr","left":40.81651010048142,"top":216.17449443077933,"start":[0,0],"end":[540.4804270462632,0],"points":["",""],"color":"rgb(155, 0, 0)","style":"solid","width":2,"lock":true},{"type":"shape","id":"Pd2LQY4J2h","left":14.2,"top":14.1,"width":36.65230204626337,"height":36.65230204626337,"viewBox":[36.65230204626337,36.65230204626337],"path":"M 0 0 L 0 36.65230204626337 L 36.65230204626337 36.65230204626337 L 36.65230204626337 32.98707184163703 L 3.6652302046263374 32.98707184163703 L 3.6652302046263374 0 Z","fill":"rgb(155, 0, 0)","fixedRatio":false,"rotate":90,"pathFormula":"L","keypoints":[0.1],"lock":true},{"type":"shape","id":"jYib_sCp4Q","left":14.2,"top":513.3,"width":36.65230204626337,"height":36.65230204626337,"viewBox":[36.65230204626337,36.65230204626337],"path":"M 0 0 L 0 36.65230204626337 L 36.65230204626337 36.65230204626337 L 36.65230204626337 32.98707184163703 L 3.6652302046263374 32.98707184163703 L 3.6652302046263374 0 Z","fill":"rgb(155, 0, 0)","fixedRatio":false,"rotate":0,"pathFormula":"L","keypoints":[0.1],"lock":true},{"type":"text","id":"kyvUz3BtoZ","left":900.3591427674274,"top":413.5293463470798,"width":157.00230270043963,"height":44,"content":"","rotate":0,"defaultFontName":"","defaultColor":"#333","vertical":false}],"background":{"type":"solid","color":"#fff"},"type":"content"},{"id":"rAAjqeMjyw","elements":[{"type":"shape","id":"sbx5IuDoGQ","left":0,"top":0,"width":1000,"height":281.25,"viewBox":[200,200],"path":"M 0 0 L 200 0 L 200 200 L 0 200 Z","fill":"rgb(155, 0, 0)","fixedRatio":false,"rotate":0,"lock":true},{"type":"shape","id":"5FW6ltFumY","left":0,"top":281.25,"width":1000,"height":281.25,"viewBox":[200,200],"path":"M 0 0 L 200 0 L 200 200 L 0 200 Z","fill":"rgb(242, 242, 242)","fixedRatio":false,"rotate":0,"lock":true},{"type":"shape","id":"-vds5fnFyB","left":40,"top":40,"width":920,"height":482,"viewBox":[200,200],"path":"M 0 0 L 200 0 L 200 200 L 0 200 Z","fill":"#ffffff","fixedRatio":false,"rotate":0,"shadow":{"h":4,"v":4,"blur":8,"color":"rgba(128, 128, 128, 0.13)"},"lock":true},{"type":"text","id":"UUp5Z_uaYs","left":90.00000000000006,"top":170,"width":820,"height":101,"content":"<p style=\"text-align: center;\"><strong><span style=\"font-size: 54px;\">谢谢聆听 THANKS</span></strong></p>","rotate":0,"defaultFontName":"","defaultColor":"#333","vertical":false},{"type":"line","id":"bh11k8QG4u","left":350.60201660735464,"top":281.25,"start":[0,0],"end":[298.79596678529066,0],"points":["",""],"color":"rgb(155, 0, 0)","style":"solid","width":1},{"type":"text","id":"3ouq_lCf_F","left":419.99999999999994,"top":308.4282325029656,"width":160,"height":44,"content":"<p style=\"text-align: center;\"><em><span style=\"font-size: 16px;\">演讲人：XXX</span></em></p>","rotate":0,"defaultFontName":"","defaultColor":"#333","vertical":false},{"type":"shape","id":"3y1nK04lbk","left":53.347697953736684,"top":472.90878929418744,"width":36.65230204626337,"height":36.65230204626337,"viewBox":[36.65230204626337,36.65230204626337],"path":"M 0 0 L 0 36.65230204626337 L 36.65230204626337 36.65230204626337 L 36.65230204626337 32.98707184163703 L 3.6652302046263374 32.98707184163703 L 3.6652302046263374 0 Z","fill":"rgb(155, 0, 0)","fixedRatio":false,"rotate":0,"pathFormula":"L","keypoints":[0.1],"lock":true},{"type":"shape","id":"Aw_f4UN1aE","left":910,"top":472.90878929418744,"width":36.65230204626337,"height":36.65230204626337,"viewBox":[36.65230204626337,36.65230204626337],"path":"M 0 0 L 0 36.65230204626337 L 36.65230204626337 36.65230204626337 L 36.65230204626337 32.98707184163703 L 3.6652302046263374 32.98707184163703 L 3.6652302046263374 0 Z","fill":"rgb(155, 0, 0)","fixedRatio":false,"rotate":-90,"pathFormula":"L","keypoints":[0.1],"lock":true},{"type":"shape","id":"Av2_nmozHh","left":910,"top":54.37972642348757,"width":36.65230204626337,"height":36.65230204626337,"viewBox":[36.65230204626337,36.65230204626337],"path":"M 0 0 L 0 36.65230204626337 L 36.65230204626337 36.65230204626337 L 36.65230204626337 32.98707184163703 L 3.6652302046263374 32.98707184163703 L 3.6652302046263374 0 Z","fill":"rgb(155, 0, 0)","fixedRatio":false,"rotate":180,"pathFormula":"L","keypoints":[0.1],"lock":true},{"type":"shape","id":"bvzwM5OOA-","left":53.347697953736684,"top":54.37972642348757,"width":36.65230204626337,"height":36.65230204626337,"viewBox":[36.65230204626337,36.65230204626337],"path":"M 0 0 L 0 36.65230204626337 L 36.65230204626337 36.65230204626337 L 36.65230204626337 32.98707184163703 L 3.6652302046263374 32.98707184163703 L 3.6652302046263374 0 Z","fill":"rgb(155, 0, 0)","fixedRatio":false,"rotate":90,"pathFormula":"L","keypoints":[0.1],"lock":true}],"background":{"type":"solid","color":"#fff"},"type":"end"}]}